{"primaryContentSections":[{"kind":"declarations","declarations":[{"tokens":[{"kind":"keyword","text":"convenience"},{"kind":"text","text":" "},{"kind":"keyword","text":"init"},{"kind":"text","text":"("},{"kind":"externalParam","text":"channelListTheme"},{"kind":"text","text":": "},{"kind":"typeIdentifier","identifier":"doc:\/\/com.sendbird.uikit\/documentation\/SendbirdUIKit\/SBUGroupChannelListTheme","preciseIdentifier":"s:13SendbirdUIKit24SBUGroupChannelListThemeC","text":"SBUGroupChannelListTheme"},{"kind":"text","text":" = .light, "},{"kind":"externalParam","text":"channelCellTheme"},{"kind":"text","text":": "},{"kind":"typeIdentifier","identifier":"doc:\/\/com.sendbird.uikit\/documentation\/SendbirdUIKit\/SBUGroupChannelCellTheme","preciseIdentifier":"s:13SendbirdUIKit24SBUGroupChannelCellThemeC","text":"SBUGroupChannelCellTheme"},{"kind":"text","text":" = .light, "},{"kind":"externalParam","text":"openChannelListTheme"},{"kind":"text","text":": "},{"kind":"typeIdentifier","identifier":"doc:\/\/com.sendbird.uikit\/documentation\/SendbirdUIKit\/SBUOpenChannelListTheme","preciseIdentifier":"s:13SendbirdUIKit23SBUOpenChannelListThemeC","text":"SBUOpenChannelListTheme"},{"kind":"text","text":" = .light, "},{"kind":"externalParam","text":"openChannelCellTheme"},{"kind":"text","text":": "},{"kind":"typeIdentifier","identifier":"doc:\/\/com.sendbird.uikit\/documentation\/SendbirdUIKit\/SBUOpenChannelCellTheme","preciseIdentifier":"s:13SendbirdUIKit23SBUOpenChannelCellThemeC","text":"SBUOpenChannelCellTheme"},{"kind":"text","text":" = .light, "},{"kind":"externalParam","text":"channelTheme"},{"kind":"text","text":": "},{"kind":"typeIdentifier","identifier":"doc:\/\/com.sendbird.uikit\/documentation\/SendbirdUIKit\/SBUChannelTheme","preciseIdentifier":"s:13SendbirdUIKit15SBUChannelThemeC","text":"SBUChannelTheme"},{"kind":"text","text":" = .light, "},{"kind":"externalParam","text":"messageInputTheme"},{"kind":"text","text":": "},{"kind":"typeIdentifier","identifier":"doc:\/\/com.sendbird.uikit\/documentation\/SendbirdUIKit\/SBUMessageInputTheme","preciseIdentifier":"s:13SendbirdUIKit20SBUMessageInputThemeC","text":"SBUMessageInputTheme"},{"kind":"text","text":" = .light, "},{"kind":"externalParam","text":"messageCellTheme"},{"kind":"text","text":": "},{"kind":"typeIdentifier","identifier":"doc:\/\/com.sendbird.uikit\/documentation\/SendbirdUIKit\/SBUMessageCellTheme","preciseIdentifier":"s:13SendbirdUIKit19SBUMessageCellThemeC","text":"SBUMessageCellTheme"},{"kind":"text","text":" = .light, "},{"kind":"externalParam","text":"userListTheme"},{"kind":"text","text":": "},{"kind":"typeIdentifier","identifier":"doc:\/\/com.sendbird.uikit\/documentation\/SendbirdUIKit\/SBUUserListTheme","preciseIdentifier":"s:13SendbirdUIKit16SBUUserListThemeC","text":"SBUUserListTheme"},{"kind":"text","text":" = .light, "},{"kind":"externalParam","text":"userCellTheme"},{"kind":"text","text":": "},{"kind":"typeIdentifier","identifier":"doc:\/\/com.sendbird.uikit\/documentation\/SendbirdUIKit\/SBUUserCellTheme","preciseIdentifier":"s:13SendbirdUIKit16SBUUserCellThemeC","text":"SBUUserCellTheme"},{"kind":"text","text":" = .light, "},{"kind":"externalParam","text":"channelSettingsTheme"},{"kind":"text","text":": "},{"kind":"typeIdentifier","identifier":"doc:\/\/com.sendbird.uikit\/documentation\/SendbirdUIKit\/SBUChannelSettingsTheme","preciseIdentifier":"s:13SendbirdUIKit23SBUChannelSettingsThemeC","text":"SBUChannelSettingsTheme"},{"kind":"text","text":" = .light, "},{"kind":"externalParam","text":"userProfileTheme"},{"kind":"text","text":": "},{"kind":"typeIdentifier","identifier":"doc:\/\/com.sendbird.uikit\/documentation\/SendbirdUIKit\/SBUUserProfileTheme","preciseIdentifier":"s:13SendbirdUIKit19SBUUserProfileThemeC","text":"SBUUserProfileTheme"},{"kind":"text","text":" = .light, "},{"kind":"externalParam","text":"componentTheme"},{"kind":"text","text":": "},{"kind":"typeIdentifier","identifier":"doc:\/\/com.sendbird.uikit\/documentation\/SendbirdUIKit\/SBUComponentTheme","preciseIdentifier":"s:13SendbirdUIKit17SBUComponentThemeC","text":"SBUComponentTheme"},{"kind":"text","text":" = .light, "},{"kind":"externalParam","text":"overlayTheme"},{"kind":"text","text":": "},{"kind":"typeIdentifier","identifier":"doc:\/\/com.sendbird.uikit\/documentation\/SendbirdUIKit\/SBUOverlayTheme","preciseIdentifier":"s:13SendbirdUIKit15SBUOverlayThemeC","text":"SBUOverlayTheme"},{"kind":"text","text":" = .init(), "},{"kind":"externalParam","text":"messageSearchTheme"},{"kind":"text","text":": "},{"kind":"typeIdentifier","identifier":"doc:\/\/com.sendbird.uikit\/documentation\/SendbirdUIKit\/SBUMessageSearchTheme","preciseIdentifier":"s:13SendbirdUIKit21SBUMessageSearchThemeC","text":"SBUMessageSearchTheme"},{"kind":"text","text":" = .light, "},{"kind":"externalParam","text":"messageSearchResultCellTheme"},{"kind":"text","text":": "},{"kind":"typeIdentifier","identifier":"doc:\/\/com.sendbird.uikit\/documentation\/SendbirdUIKit\/SBUMessageSearchResultCellTheme","preciseIdentifier":"s:13SendbirdUIKit31SBUMessageSearchResultCellThemeC","text":"SBUMessageSearchResultCellTheme"},{"kind":"text","text":" = .light, "},{"kind":"externalParam","text":"createOpenChannelTheme"},{"kind":"text","text":": "},{"kind":"typeIdentifier","identifier":"doc:\/\/com.sendbird.uikit\/documentation\/SendbirdUIKit\/SBUCreateOpenChannelTheme","preciseIdentifier":"s:13SendbirdUIKit25SBUCreateOpenChannelThemeC","text":"SBUCreateOpenChannelTheme"},{"kind":"text","text":" = .light)"}],"languages":["swift"],"platforms":["iOS"]}]}],"schemaVersion":{"major":0,"minor":2,"patch":0},"sections":[],"variants":[{"paths":["\/documentation\/sendbirduikit\/sbutheme\/init(channellisttheme:channelcelltheme:openchannellisttheme:openchannelcelltheme:channeltheme:messageinputtheme:messagecelltheme:userlisttheme:usercelltheme:channelsettingstheme:userprofiletheme:componenttheme:overlaytheme:messagesearchthem-302uv"],"traits":[{"interfaceLanguage":"swift"}]}],"identifier":{"url":"doc:\/\/com.sendbird.uikit\/documentation\/SendbirdUIKit\/SBUTheme\/init(channelListTheme:channelCellTheme:openChannelListTheme:openChannelCellTheme:channelTheme:messageInputTheme:messageCellTheme:userListTheme:userCellTheme:channelSettingsTheme:userProfileTheme:componentTheme:overlayTheme:messageSearchTheme:messageSearchResultCellTheme:createOpenChannelTheme:)","interfaceLanguage":"swift"},"abstract":[{"type":"text","text":"No overview available."}],"kind":"symbol","metadata":{"modules":[{"name":"SendbirdUIKit"}],"role":"symbol","title":"init(channelListTheme:channelCellTheme:openChannelListTheme:openChannelCellTheme:channelTheme:messageInputTheme:messageCellTheme:userListTheme:userCellTheme:channelSettingsTheme:userProfileTheme:componentTheme:overlayTheme:messageSearchTheme:messageSearchResultCellTheme:createOpenChannelTheme:)","roleHeading":"Initializer","fragments":[{"kind":"identifier","text":"init"},{"kind":"text","text":"("},{"kind":"externalParam","text":"channelListTheme"},{"kind":"text","text":": "},{"kind":"typeIdentifier","text":"SBUGroupChannelListTheme","preciseIdentifier":"s:13SendbirdUIKit24SBUGroupChannelListThemeC"},{"kind":"text","text":", "},{"kind":"externalParam","text":"channelCellTheme"},{"kind":"text","text":": "},{"kind":"typeIdentifier","text":"SBUGroupChannelCellTheme","preciseIdentifier":"s:13SendbirdUIKit24SBUGroupChannelCellThemeC"},{"kind":"text","text":", "},{"kind":"externalParam","text":"openChannelListTheme"},{"kind":"text","text":": "},{"kind":"typeIdentifier","text":"SBUOpenChannelListTheme","preciseIdentifier":"s:13SendbirdUIKit23SBUOpenChannelListThemeC"},{"kind":"text","text":", "},{"kind":"externalParam","text":"openChannelCellTheme"},{"kind":"text","text":": "},{"kind":"typeIdentifier","text":"SBUOpenChannelCellTheme","preciseIdentifier":"s:13SendbirdUIKit23SBUOpenChannelCellThemeC"},{"kind":"text","text":", "},{"kind":"externalParam","text":"channelTheme"},{"kind":"text","text":": "},{"kind":"typeIdentifier","text":"SBUChannelTheme","preciseIdentifier":"s:13SendbirdUIKit15SBUChannelThemeC"},{"kind":"text","text":", "},{"kind":"externalParam","text":"messageInputTheme"},{"kind":"text","text":": "},{"kind":"typeIdentifier","text":"SBUMessageInputTheme","preciseIdentifier":"s:13SendbirdUIKit20SBUMessageInputThemeC"},{"kind":"text","text":", "},{"kind":"externalParam","text":"messageCellTheme"},{"kind":"text","text":": "},{"kind":"typeIdentifier","text":"SBUMessageCellTheme","preciseIdentifier":"s:13SendbirdUIKit19SBUMessageCellThemeC"},{"kind":"text","text":", "},{"kind":"externalParam","text":"userListTheme"},{"kind":"text","text":": "},{"kind":"typeIdentifier","text":"SBUUserListTheme","preciseIdentifier":"s:13SendbirdUIKit16SBUUserListThemeC"},{"kind":"text","text":", "},{"kind":"externalParam","text":"userCellTheme"},{"kind":"text","text":": "},{"kind":"typeIdentifier","text":"SBUUserCellTheme","preciseIdentifier":"s:13SendbirdUIKit16SBUUserCellThemeC"},{"kind":"text","text":", "},{"kind":"externalParam","text":"channelSettingsTheme"},{"kind":"text","text":": "},{"kind":"typeIdentifier","text":"SBUChannelSettingsTheme","preciseIdentifier":"s:13SendbirdUIKit23SBUChannelSettingsThemeC"},{"kind":"text","text":", "},{"kind":"externalParam","text":"userProfileTheme"},{"kind":"text","text":": "},{"kind":"typeIdentifier","text":"SBUUserProfileTheme","preciseIdentifier":"s:13SendbirdUIKit19SBUUserProfileThemeC"},{"kind":"text","text":", "},{"kind":"externalParam","text":"componentTheme"},{"kind":"text","text":": "},{"kind":"typeIdentifier","text":"SBUComponentTheme","preciseIdentifier":"s:13SendbirdUIKit17SBUComponentThemeC"},{"kind":"text","text":", "},{"kind":"externalParam","text":"overlayTheme"},{"kind":"text","text":": "},{"kind":"typeIdentifier","text":"SBUOverlayTheme","preciseIdentifier":"s:13SendbirdUIKit15SBUOverlayThemeC"},{"kind":"text","text":", "},{"kind":"externalParam","text":"messageSearchTheme"},{"kind":"text","text":": "},{"kind":"typeIdentifier","text":"SBUMessageSearchTheme","preciseIdentifier":"s:13SendbirdUIKit21SBUMessageSearchThemeC"},{"kind":"text","text":", "},{"kind":"externalParam","text":"messageSearchResultCellTheme"},{"kind":"text","text":": "},{"kind":"typeIdentifier","text":"SBUMessageSearchResultCellTheme","preciseIdentifier":"s:13SendbirdUIKit31SBUMessageSearchResultCellThemeC"},{"kind":"text","text":", "},{"kind":"externalParam","text":"createOpenChannelTheme"},{"kind":"text","text":": "},{"kind":"typeIdentifier","text":"SBUCreateOpenChannelTheme","preciseIdentifier":"s:13SendbirdUIKit25SBUCreateOpenChannelThemeC"},{"kind":"text","text":")"}],"symbolKind":"init","externalID":"s:13SendbirdUIKit8SBUThemeC16channelListTheme0d4CellF0011openChanneleF00higF00dF0012messageInputF00jgF004usereF00lgF00d8SettingsF00l7ProfileF009componentF007overlayF00j6SearchF00jq6ResultgF0010createOpeniF0AcA08SBUGroupieF0C_AA0uigF0CAA07SBUOpenieF0CAA0vigF0CAA010SBUChannelF0CAA010SBUMessagekF0CAA0xgF0CAA07SBUUsereF0CAA0ygF0CAA0wmF0CAA0ynF0CAA012SBUComponentF0CAA010SBUOverlayF0CAA0xqF0CAA0xqrgF0CAA09SBUCreatetiF0Ctcfc","extendedModule":"SendbirdUIKit","platforms":[]},"hierarchy":{"paths":[["doc:\/\/com.sendbird.uikit\/documentation\/SendbirdUIKit","doc:\/\/com.sendbird.uikit\/documentation\/SendbirdUIKit\/SBUTheme"]]},"references":{"doc://com.sendbird.uikit/documentation/SendbirdUIKit/SBUOpenChannelCellTheme":{"role":"symbol","title":"SBUOpenChannelCellTheme","fragments":[{"kind":"keyword","text":"class"},{"kind":"text","text":" "},{"kind":"identifier","text":"SBUOpenChannelCellTheme"}],"abstract":[],"identifier":"doc:\/\/com.sendbird.uikit\/documentation\/SendbirdUIKit\/SBUOpenChannelCellTheme","kind":"symbol","type":"topic","navigatorTitle":[{"kind":"identifier","text":"SBUOpenChannelCellTheme"}],"url":"\/documentation\/sendbirduikit\/sbuopenchannelcelltheme"},"doc://com.sendbird.uikit/documentation/SendbirdUIKit/SBUMessageSearchTheme":{"role":"symbol","title":"SBUMessageSearchTheme","fragments":[{"kind":"keyword","text":"class"},{"kind":"text","text":" "},{"kind":"identifier","text":"SBUMessageSearchTheme"}],"abstract":[],"identifier":"doc:\/\/com.sendbird.uikit\/documentation\/SendbirdUIKit\/SBUMessageSearchTheme","kind":"symbol","type":"topic","navigatorTitle":[{"kind":"identifier","text":"SBUMessageSearchTheme"}],"url":"\/documentation\/sendbirduikit\/sbumessagesearchtheme"},"doc://com.sendbird.uikit/documentation/SendbirdUIKit/SBUGroupChannelListTheme":{"role":"symbol","title":"SBUGroupChannelListTheme","fragments":[{"kind":"keyword","text":"class"},{"kind":"text","text":" "},{"kind":"identifier","text":"SBUGroupChannelListTheme"}],"abstract":[],"identifier":"doc:\/\/com.sendbird.uikit\/documentation\/SendbirdUIKit\/SBUGroupChannelListTheme","kind":"symbol","type":"topic","navigatorTitle":[{"kind":"identifier","text":"SBUGroupChannelListTheme"}],"url":"\/documentation\/sendbirduikit\/sbugroupchannellisttheme"},"doc://com.sendbird.uikit/documentation/SendbirdUIKit/SBUUserCellTheme":{"role":"symbol","title":"SBUUserCellTheme","fragments":[{"kind":"keyword","text":"class"},{"kind":"text","text":" "},{"kind":"identifier","text":"SBUUserCellTheme"}],"abstract":[],"identifier":"doc:\/\/com.sendbird.uikit\/documentation\/SendbirdUIKit\/SBUUserCellTheme","kind":"symbol","type":"topic","navigatorTitle":[{"kind":"identifier","text":"SBUUserCellTheme"}],"url":"\/documentation\/sendbirduikit\/sbuusercelltheme"},"doc://com.sendbird.uikit/documentation/SendbirdUIKit/SBUUserProfileTheme":{"role":"symbol","title":"SBUUserProfileTheme","fragments":[{"kind":"keyword","text":"class"},{"kind":"text","text":" "},{"kind":"identifier","text":"SBUUserProfileTheme"}],"abstract":[],"identifier":"doc:\/\/com.sendbird.uikit\/documentation\/SendbirdUIKit\/SBUUserProfileTheme","kind":"symbol","type":"topic","navigatorTitle":[{"kind":"identifier","text":"SBUUserProfileTheme"}],"url":"\/documentation\/sendbirduikit\/sbuuserprofiletheme"},"doc://com.sendbird.uikit/documentation/SendbirdUIKit/SBUChannelSettingsTheme":{"role":"symbol","title":"SBUChannelSettingsTheme","fragments":[{"kind":"keyword","text":"class"},{"kind":"text","text":" "},{"kind":"identifier","text":"SBUChannelSettingsTheme"}],"abstract":[],"identifier":"doc:\/\/com.sendbird.uikit\/documentation\/SendbirdUIKit\/SBUChannelSettingsTheme","kind":"symbol","type":"topic","navigatorTitle":[{"kind":"identifier","text":"SBUChannelSettingsTheme"}],"url":"\/documentation\/sendbirduikit\/sbuchannelsettingstheme"},"doc://com.sendbird.uikit/documentation/SendbirdUIKit/SBUUserListTheme":{"role":"symbol","title":"SBUUserListTheme","fragments":[{"kind":"keyword","text":"class"},{"kind":"text","text":" "},{"kind":"identifier","text":"SBUUserListTheme"}],"abstract":[],"identifier":"doc:\/\/com.sendbird.uikit\/documentation\/SendbirdUIKit\/SBUUserListTheme","kind":"symbol","type":"topic","navigatorTitle":[{"kind":"identifier","text":"SBUUserListTheme"}],"url":"\/documentation\/sendbirduikit\/sbuuserlisttheme"},"doc://com.sendbird.uikit/documentation/SendbirdUIKit":{"role":"collection","title":"SendbirdUIKit","abstract":[{"type":"text","text":"Sendbird UIKit for iOS"}],"identifier":"doc:\/\/com.sendbird.uikit\/documentation\/SendbirdUIKit","kind":"symbol","type":"topic","url":"\/documentation\/sendbirduikit"},"doc://com.sendbird.uikit/documentation/SendbirdUIKit/SBUMessageSearchResultCellTheme":{"role":"symbol","title":"SBUMessageSearchResultCellTheme","fragments":[{"kind":"keyword","text":"class"},{"kind":"text","text":" "},{"kind":"identifier","text":"SBUMessageSearchResultCellTheme"}],"abstract":[],"identifier":"doc:\/\/com.sendbird.uikit\/documentation\/SendbirdUIKit\/SBUMessageSearchResultCellTheme","kind":"symbol","type":"topic","navigatorTitle":[{"kind":"identifier","text":"SBUMessageSearchResultCellTheme"}],"url":"\/documentation\/sendbirduikit\/sbumessagesearchresultcelltheme"},"doc://com.sendbird.uikit/documentation/SendbirdUIKit/SBUChannelTheme":{"role":"symbol","title":"SBUChannelTheme","fragments":[{"kind":"keyword","text":"class"},{"kind":"text","text":" "},{"kind":"identifier","text":"SBUChannelTheme"}],"abstract":[],"identifier":"doc:\/\/com.sendbird.uikit\/documentation\/SendbirdUIKit\/SBUChannelTheme","kind":"symbol","type":"topic","navigatorTitle":[{"kind":"identifier","text":"SBUChannelTheme"}],"url":"\/documentation\/sendbirduikit\/sbuchanneltheme"},"doc://com.sendbird.uikit/documentation/SendbirdUIKit/SBUTheme/init(channelListTheme:channelCellTheme:openChannelListTheme:openChannelCellTheme:channelTheme:messageInputTheme:messageCellTheme:userListTheme:userCellTheme:channelSettingsTheme:userProfileTheme:componentTheme:overlayTheme:messageSearchTheme:messageSearchResultCellTheme:createOpenChannelTheme:)":{"role":"symbol","title":"init(channelListTheme:channelCellTheme:openChannelListTheme:openChannelCellTheme:channelTheme:messageInputTheme:messageCellTheme:userListTheme:userCellTheme:channelSettingsTheme:userProfileTheme:componentTheme:overlayTheme:messageSearchTheme:messageSearchResultCellTheme:createOpenChannelTheme:)","fragments":[{"kind":"identifier","text":"init"},{"kind":"text","text":"("},{"kind":"externalParam","text":"channelListTheme"},{"kind":"text","text":": "},{"kind":"typeIdentifier","text":"SBUGroupChannelListTheme","preciseIdentifier":"s:13SendbirdUIKit24SBUGroupChannelListThemeC"},{"kind":"text","text":", "},{"kind":"externalParam","text":"channelCellTheme"},{"kind":"text","text":": "},{"kind":"typeIdentifier","text":"SBUGroupChannelCellTheme","preciseIdentifier":"s:13SendbirdUIKit24SBUGroupChannelCellThemeC"},{"kind":"text","text":", "},{"kind":"externalParam","text":"openChannelListTheme"},{"kind":"text","text":": "},{"kind":"typeIdentifier","text":"SBUOpenChannelListTheme","preciseIdentifier":"s:13SendbirdUIKit23SBUOpenChannelListThemeC"},{"kind":"text","text":", "},{"kind":"externalParam","text":"openChannelCellTheme"},{"kind":"text","text":": "},{"kind":"typeIdentifier","text":"SBUOpenChannelCellTheme","preciseIdentifier":"s:13SendbirdUIKit23SBUOpenChannelCellThemeC"},{"kind":"text","text":", "},{"kind":"externalParam","text":"channelTheme"},{"kind":"text","text":": "},{"kind":"typeIdentifier","text":"SBUChannelTheme","preciseIdentifier":"s:13SendbirdUIKit15SBUChannelThemeC"},{"kind":"text","text":", "},{"kind":"externalParam","text":"messageInputTheme"},{"kind":"text","text":": "},{"kind":"typeIdentifier","text":"SBUMessageInputTheme","preciseIdentifier":"s:13SendbirdUIKit20SBUMessageInputThemeC"},{"kind":"text","text":", "},{"kind":"externalParam","text":"messageCellTheme"},{"kind":"text","text":": "},{"kind":"typeIdentifier","text":"SBUMessageCellTheme","preciseIdentifier":"s:13SendbirdUIKit19SBUMessageCellThemeC"},{"kind":"text","text":", "},{"kind":"externalParam","text":"userListTheme"},{"kind":"text","text":": "},{"kind":"typeIdentifier","text":"SBUUserListTheme","preciseIdentifier":"s:13SendbirdUIKit16SBUUserListThemeC"},{"kind":"text","text":", "},{"kind":"externalParam","text":"userCellTheme"},{"kind":"text","text":": "},{"kind":"typeIdentifier","text":"SBUUserCellTheme","preciseIdentifier":"s:13SendbirdUIKit16SBUUserCellThemeC"},{"kind":"text","text":", "},{"kind":"externalParam","text":"channelSettingsTheme"},{"kind":"text","text":": "},{"kind":"typeIdentifier","text":"SBUChannelSettingsTheme","preciseIdentifier":"s:13SendbirdUIKit23SBUChannelSettingsThemeC"},{"kind":"text","text":", "},{"kind":"externalParam","text":"userProfileTheme"},{"kind":"text","text":": "},{"kind":"typeIdentifier","text":"SBUUserProfileTheme","preciseIdentifier":"s:13SendbirdUIKit19SBUUserProfileThemeC"},{"kind":"text","text":", "},{"kind":"externalParam","text":"componentTheme"},{"kind":"text","text":": "},{"kind":"typeIdentifier","text":"SBUComponentTheme","preciseIdentifier":"s:13SendbirdUIKit17SBUComponentThemeC"},{"kind":"text","text":", "},{"kind":"externalParam","text":"overlayTheme"},{"kind":"text","text":": "},{"kind":"typeIdentifier","text":"SBUOverlayTheme","preciseIdentifier":"s:13SendbirdUIKit15SBUOverlayThemeC"},{"kind":"text","text":", "},{"kind":"externalParam","text":"messageSearchTheme"},{"kind":"text","text":": "},{"kind":"typeIdentifier","text":"SBUMessageSearchTheme","preciseIdentifier":"s:13SendbirdUIKit21SBUMessageSearchThemeC"},{"kind":"text","text":", "},{"kind":"externalParam","text":"messageSearchResultCellTheme"},{"kind":"text","text":": "},{"kind":"typeIdentifier","text":"SBUMessageSearchResultCellTheme","preciseIdentifier":"s:13SendbirdUIKit31SBUMessageSearchResultCellThemeC"},{"kind":"text","text":", "},{"kind":"externalParam","text":"createOpenChannelTheme"},{"kind":"text","text":": "},{"kind":"typeIdentifier","text":"SBUCreateOpenChannelTheme","preciseIdentifier":"s:13SendbirdUIKit25SBUCreateOpenChannelThemeC"},{"kind":"text","text":")"}],"abstract":[],"identifier":"doc:\/\/com.sendbird.uikit\/documentation\/SendbirdUIKit\/SBUTheme\/init(channelListTheme:channelCellTheme:openChannelListTheme:openChannelCellTheme:channelTheme:messageInputTheme:messageCellTheme:userListTheme:userCellTheme:channelSettingsTheme:userProfileTheme:componentTheme:overlayTheme:messageSearchTheme:messageSearchResultCellTheme:createOpenChannelTheme:)","kind":"symbol","type":"topic","deprecated":true,"url":"\/documentation\/sendbirduikit\/sbutheme\/init(channellisttheme:channelcelltheme:openchannellisttheme:openchannelcelltheme:channeltheme:messageinputtheme:messagecelltheme:userlisttheme:usercelltheme:channelsettingstheme:userprofiletheme:componenttheme:overlaytheme:messagesearchthem-302uv"},"doc://com.sendbird.uikit/documentation/SendbirdUIKit/SBUGroupChannelCellTheme":{"role":"symbol","title":"SBUGroupChannelCellTheme","fragments":[{"kind":"keyword","text":"class"},{"kind":"text","text":" "},{"kind":"identifier","text":"SBUGroupChannelCellTheme"}],"abstract":[],"identifier":"doc:\/\/com.sendbird.uikit\/documentation\/SendbirdUIKit\/SBUGroupChannelCellTheme","kind":"symbol","type":"topic","navigatorTitle":[{"kind":"identifier","text":"SBUGroupChannelCellTheme"}],"url":"\/documentation\/sendbirduikit\/sbugroupchannelcelltheme"},"doc://com.sendbird.uikit/documentation/SendbirdUIKit/SBUMessageCellTheme":{"role":"symbol","title":"SBUMessageCellTheme","fragments":[{"kind":"keyword","text":"class"},{"kind":"text","text":" "},{"kind":"identifier","text":"SBUMessageCellTheme"}],"abstract":[],"identifier":"doc:\/\/com.sendbird.uikit\/documentation\/SendbirdUIKit\/SBUMessageCellTheme","kind":"symbol","type":"topic","navigatorTitle":[{"kind":"identifier","text":"SBUMessageCellTheme"}],"url":"\/documentation\/sendbirduikit\/sbumessagecelltheme"},"doc://com.sendbird.uikit/documentation/SendbirdUIKit/SBUOpenChannelListTheme":{"role":"symbol","title":"SBUOpenChannelListTheme","fragments":[{"kind":"keyword","text":"class"},{"kind":"text","text":" "},{"kind":"identifier","text":"SBUOpenChannelListTheme"}],"abstract":[],"identifier":"doc:\/\/com.sendbird.uikit\/documentation\/SendbirdUIKit\/SBUOpenChannelListTheme","kind":"symbol","type":"topic","navigatorTitle":[{"kind":"identifier","text":"SBUOpenChannelListTheme"}],"url":"\/documentation\/sendbirduikit\/sbuopenchannellisttheme"},"doc://com.sendbird.uikit/documentation/SendbirdUIKit/SBUOverlayTheme":{"role":"symbol","title":"SBUOverlayTheme","fragments":[{"kind":"keyword","text":"class"},{"kind":"text","text":" "},{"kind":"identifier","text":"SBUOverlayTheme"}],"abstract":[],"identifier":"doc:\/\/com.sendbird.uikit\/documentation\/SendbirdUIKit\/SBUOverlayTheme","kind":"symbol","type":"topic","navigatorTitle":[{"kind":"identifier","text":"SBUOverlayTheme"}],"url":"\/documentation\/sendbirduikit\/sbuoverlaytheme"},"doc://com.sendbird.uikit/documentation/SendbirdUIKit/SBUTheme":{"role":"symbol","title":"SBUTheme","fragments":[{"kind":"keyword","text":"class"},{"kind":"text","text":" "},{"kind":"identifier","text":"SBUTheme"}],"abstract":[],"identifier":"doc:\/\/com.sendbird.uikit\/documentation\/SendbirdUIKit\/SBUTheme","kind":"symbol","type":"topic","navigatorTitle":[{"kind":"identifier","text":"SBUTheme"}],"url":"\/documentation\/sendbirduikit\/sbutheme"},"doc://com.sendbird.uikit/documentation/SendbirdUIKit/SBUMessageInputTheme":{"role":"symbol","title":"SBUMessageInputTheme","fragments":[{"kind":"keyword","text":"class"},{"kind":"text","text":" "},{"kind":"identifier","text":"SBUMessageInputTheme"}],"abstract":[],"identifier":"doc:\/\/com.sendbird.uikit\/documentation\/SendbirdUIKit\/SBUMessageInputTheme","kind":"symbol","type":"topic","navigatorTitle":[{"kind":"identifier","text":"SBUMessageInputTheme"}],"url":"\/documentation\/sendbirduikit\/sbumessageinputtheme"},"doc://com.sendbird.uikit/documentation/SendbirdUIKit/SBUCreateOpenChannelTheme":{"role":"symbol","title":"SBUCreateOpenChannelTheme","fragments":[{"kind":"keyword","text":"class"},{"kind":"text","text":" "},{"kind":"identifier","text":"SBUCreateOpenChannelTheme"}],"abstract":[],"identifier":"doc:\/\/com.sendbird.uikit\/documentation\/SendbirdUIKit\/SBUCreateOpenChannelTheme","kind":"symbol","type":"topic","navigatorTitle":[{"kind":"identifier","text":"SBUCreateOpenChannelTheme"}],"url":"\/documentation\/sendbirduikit\/sbucreateopenchanneltheme"},"doc://com.sendbird.uikit/documentation/SendbirdUIKit/SBUComponentTheme":{"role":"symbol","title":"SBUComponentTheme","fragments":[{"kind":"keyword","text":"class"},{"kind":"text","text":" "},{"kind":"identifier","text":"SBUComponentTheme"}],"abstract":[],"identifier":"doc:\/\/com.sendbird.uikit\/documentation\/SendbirdUIKit\/SBUComponentTheme","kind":"symbol","type":"topic","navigatorTitle":[{"kind":"identifier","text":"SBUComponentTheme"}],"url":"\/documentation\/sendbirduikit\/sbucomponenttheme"}}}